{
  "data": [
    {
      "city": "西安",
      "swiperList": [
        {
          "id": "01",
          "imgUrl": "/api/images/bg01.jpg"
        },
        {
          "id": "02",
          "imgUrl": "/api/images/bg02.jpg"
        },
        {
          "id": "03",
          "imgUrl": "/api/images/bg03.jpg"
        }
      ],
      "iconsList": [
        {
          "id": "01",
          "iconsURL": "/api/icons/icon01.png",
          "title": "找攻略"
        },
        {
          "id": "01",
          "iconsURL": "/api/icons/icon02.png",
          "title": "看游记"
        },
        {
          "id": "01",
          "iconsURL": "/api/icons/icon03.png",
          "title": "问达人"
        },
        {
          "id": "01",
          "iconsURL": "/api/icons/icon04.png",
          "title": "头脑学园"
        },
        {
          "id": "01",
          "iconsURL": "/api/icons/icon05.png",
          "title": "酒店"
        },
        {
          "id": "01",
          "iconsURL": "/api/icons/icon06.png",
          "title": "去旅行"
        },
        {
          "id": "01",
          "iconsURL": "/api/icons/icon07.png",
          "title": "机票"
        },
        {
          "id": "01",
          "iconsURL": "/api/icons/icon08.png",
          "title": "当地玩乐"
        }
      ],
      "hotList": [
        {
          "id": "01",
          "imgURL": "/api/images/hot01.jpg",
          "titleName": "秦始皇帝陵博物院",
          "titleDetail": "秦始皇的地下御林军",
          "price": "¥120"
        },
        {
          "id": "02",
          "imgURL": "/api/images/hot02.jpg",
          "titleName": "秦岭野生动物园",
          "titleDetail": "观看放养的各类猛兽",
          "price": "¥100"
        },
        {
          "id": "03",
          "imgURL": "/api/images/hot03.jpg",
          "titleName": "华清宫",
          "titleDetail": "唐玄宗和杨贵妃的共浴地",
          "price": "¥120"
        },
        {
          "id": "04",
          "imgURL": "/api/images/hot04.jpg",
          "titleName": "华山景区",
          "titleDetail": "'以'奇险出名的五岳之一",
          "price": "¥100"
        }
      ],
      "contentList": [
        {
          "id": "content01",
          "title": "房车自驾｜土家族姑娘的湘·黔环游记",
          "imgURL": "/api/images/like01.png",
          "summer": "题记-人总要给忙忙碌碌的生活找点不一样的乐趣，或是约一约许久不见的老朋友吃一顿火锅，或是打一场酣畅淋漓的篮球比赛，或是安静的看完一本喜欢的书，亦或是去那个一直想去却还不曾到达的远方。预告片夜晚芙蓉镇水面上的一抹红，越是平静的水面越...",
          "look": "17917",
          "author": "大大泡泡糖",
          "authorImg": "/api/images/likeheade01.jpeg"
        },
        {
          "id": "content02",
          "title": "退去神秘面纱的甘南，谁还甘心做神山的亡命之徒",
          "imgURL": "/api/images/like02.jpg",
          "summer": "前言——重走洛克之路爱上旅行之后我一直希望像洛克一般，怀着唐·吉诃德式的旅行梦想，带着电唱机听着音乐和歌剧，沿路做着植物学的笔记和宗教、人类学的记录，走在蛮荒的路上，享受一份孤独的自由。所以我相信人生真正好的东西是不可说的，就像武陵...",
          "look": "53464",
          "author": "我想发芽",
          "authorImg": "/api/images/likeheade02.jpeg"
        },
        {
          "id": "content03",
          "title": "打卡湖北恩施如诗如画的山水风光，绚丽多彩的绿色仙境",
          "imgURL": "/api/images/like03.jpg",
          "summer":
            " 序言 一说到 湖北 旅游，那么 恩施 应该是网红打卡比较多的一个地方了，被称为 中国 版 仙本那 的景点，就位于 恩施 大峡谷中的 鹤峰 屏山 峡谷。那说到 湖北 恩施 那么一定不能错过的就是 恩施 的大峡谷了，水质清澈透明，跟 仙本那 水质一样，小船在 水里 行驶，犹如漂浮在半空中似的。 恩施 大峡谷能跟 美国 科罗拉多大峡谷 的绝壁栈道相媲美。这里是清江流域山清水秀的地段，整个峡谷全长多达108米，凡是来到这里的游客，都会拍手称赞。景区标志性打卡点“一炷香”只有亲身看过了才会知道原来大自然鬼斧神工真的是那么厉害。 从空中",
          "look": "6681",
          "author": "唐伯虎",
          "authorImg": "/api/images/likeheade03.jpeg"
        },
        {
          "id": "content04",
          "title": "(拯救周末计划)成都及周边丨我和周末有个约会",
          "imgURL": "/api/images/like04.jpg",
          "summer":
            " 写在前面 一次偶尔的机会让我重逢阔别多年的 成都 ， 解锁了许多 成都 的秘密， 也开启了周边的新旅程。 当想伸出手抓住这10个月的流淌时光， 才发觉似乎有人将时光给偷走了。 看来，要用文字才能留住永恒的记忆。 不论多年后的变迁， 回忆起来： “嘿，这才是我认识的 成都 。” 我的 四川 里，没有去过 稻城 亚丁、 海螺沟 、毕棚沟感受 川西 高山低谷的壮阔，也没有南下到攀西地区见识到大 凉山 的粗犷和凛冬里难得的阳光，更没有去过剑南关体验过“一夫当关万夫莫开”的磅礴气势。更多的是周末或者凑上的三天，周游在附近城市的大街",
          "look": "275",
          "author": "kingprofessor",
          "authorImg": "/api/images/likeheade04.jpeg"
        }
      ]
    },
    {
      "city": "上海",
      "swiperList": [
        {
          "id": "01",
          "imgUrl": "/api/images/bg01.jpg"
        },
        {
          "id": "02",
          "imgUrl": "/api/images/bg02.jpg"
        },
        {
          "id": "03",
          "imgUrl": "/api/images/bg03.jpg"
        }
      ],
      "iconsList": [
        {
          "id": "01",
          "iconsURL": "/api/icons/icon01.png",
          "title": "找攻略"
        },
        {
          "id": "01",
          "iconsURL": "/api/icons/icon02.png",
          "title": "看游记"
        },
        {
          "id": "01",
          "iconsURL": "/api/icons/icon03.png",
          "title": "问达人"
        },
        {
          "id": "01",
          "iconsURL": "/api/icons/icon04.png",
          "title": "头脑学园"
        },
        {
          "id": "01",
          "iconsURL": "/api/icons/icon05.png",
          "title": "酒店"
        },
        {
          "id": "01",
          "iconsURL": "/api/icons/icon06.png",
          "title": "去旅行"
        },
        {
          "id": "01",
          "iconsURL": "/api/icons/icon07.png",
          "title": "机票"
        },
        {
          "id": "01",
          "iconsURL": "/api/icons/icon08.png",
          "title": "当地玩乐"
        }
      ],
      "hotList": [
        {
          "id": "01",
          "imgURL": "/api/images/hot01.jpg",
          "titleName": "东方明珠塔",
          "titleDetail": "可以俯瞰整个上海",
          "price": "¥120"
        },
        {
          "id": "02",
          "imgURL": "/api/images/hot02.jpg",
          "titleName": "上海野生动物园",
          "titleDetail": "观看放养的各类猛兽",
          "price": "¥100"
        },
        {
          "id": "03",
          "imgURL": "/api/images/hot03.jpg",
          "titleName": "迪士尼",
          "titleDetail": "闻名的游乐园",
          "price": "¥120"
        },
        {
          "id": "04",
          "imgURL": "/api/images/hot04.jpg",
          "titleName": "观景山",
          "titleDetail": "'以'奇险出名的人造山",
          "price": "¥100"
        }
      ],
      "contentList": [
        {
          "id": "content01",
          "title": "房车自驾｜土家族姑娘的湘·黔环游记",
          "imgURL": "/api/images/like01.png",
          "summer": "题记-人总要给忙忙碌碌的生活找点不一样的乐趣，或是约一约许久不见的老朋友吃一顿火锅，或是打一场酣畅淋漓的篮球比赛，或是安静的看完一本喜欢的书，亦或是去那个一直想去却还不曾到达的远方。预告片夜晚芙蓉镇水面上的一抹红，越是平静的水面越...",
          "look": "17917",
          "author": "大大泡泡糖",
          "authorImg": "/api/images/likeheade01.jpeg"
        },
        {
          "id": "content02",
          "title": "退去神秘面纱的甘南，谁还甘心做神山的亡命之徒",
          "imgURL": "/api/images/like02.jpg",
          "summer": "前言——重走洛克之路爱上旅行之后我一直希望像洛克一般，怀着唐·吉诃德式的旅行梦想，带着电唱机听着音乐和歌剧，沿路做着植物学的笔记和宗教、人类学的记录，走在蛮荒的路上，享受一份孤独的自由。所以我相信人生真正好的东西是不可说的，就像武陵...",
          "look": "53464",
          "author": "我想发芽",
          "authorImg": "/api/images/likeheade02.jpeg"
        },
        {
          "id": "content03",
          "title": "打卡湖北恩施如诗如画的山水风光，绚丽多彩的绿色仙境",
          "imgURL": "/api/images/like03.jpg",
          "summer":
            " 序言 一说到 湖北 旅游，那么 恩施 应该是网红打卡比较多的一个地方了，被称为 中国 版 仙本那 的景点，就位于 恩施 大峡谷中的 鹤峰 屏山 峡谷。那说到 湖北 恩施 那么一定不能错过的就是 恩施 的大峡谷了，水质清澈透明，跟 仙本那 水质一样，小船在 水里 行驶，犹如漂浮在半空中似的。 恩施 大峡谷能跟 美国 科罗拉多大峡谷 的绝壁栈道相媲美。这里是清江流域山清水秀的地段，整个峡谷全长多达108米，凡是来到这里的游客，都会拍手称赞。景区标志性打卡点“一炷香”只有亲身看过了才会知道原来大自然鬼斧神工真的是那么厉害。 从空中",
          "look": "6681",
          "author": "唐伯虎",
          "authorImg": "/api/images/likeheade03.jpeg"
        },
        {
          "id": "content04",
          "title": "(拯救周末计划)成都及周边丨我和周末有个约会",
          "imgURL": "/api/images/like04.jpg",
          "summer":
            " 写在前面 一次偶尔的机会让我重逢阔别多年的 成都 ， 解锁了许多 成都 的秘密， 也开启了周边的新旅程。 当想伸出手抓住这10个月的流淌时光， 才发觉似乎有人将时光给偷走了。 看来，要用文字才能留住永恒的记忆。 不论多年后的变迁， 回忆起来： “嘿，这才是我认识的 成都 。” 我的 四川 里，没有去过 稻城 亚丁、 海螺沟 、毕棚沟感受 川西 高山低谷的壮阔，也没有南下到攀西地区见识到大 凉山 的粗犷和凛冬里难得的阳光，更没有去过剑南关体验过“一夫当关万夫莫开”的磅礴气势。更多的是周末或者凑上的三天，周游在附近城市的大街",
          "look": "275",
          "author": "kingprofessor",
          "authorImg": "/api/images/likeheade04.jpeg"
        }
      ]
    }
  ]
}